{
    "key": "group_606a00190988d",
    "title": "Component-Icon Box Carousel",
    "fields": [
        {
            "key": "field_606a00329bada",
            "label": "Icon Box Carousel",
            "name": "icon_box_carousel",
            "type": "repeater",
            "instructions": "",
            "required": 0,
            "conditional_logic": 0,
            "wrapper": {
                "width": "",
                "class": "",
                "id": ""
            },
            "collapsed": "field_606a00489badb",
            "min": 0,
            "max": 0,
            "layout": "row",
            "button_label": "Add Icon Box",
            "sub_fields": [
                {
                    "key": "field_606a00489badb",
                    "label": "Icon Box",
                    "name": "icon_box",
                    "type": "clone",
                    "instructions": "",
                    "required": 0,
                    "conditional_logic": 0,
                    "wrapper": {
                        "width": "",
                        "class": "",
                        "id": ""
                    },
                    "clone": [
                        "group_606608d962f94"
                    ],
                    "display": "seamless",
                    "layout": "block",
                    "prefix_label": 0,
                    "prefix_name": 0
                }
            ]
        }
    ],
    "location": [
        [
            {
                "param": "post_type",
                "operator": "==",
                "value": "post"
            }
        ]
    ],
    "menu_order": 0,
    "position": "normal",
    "style": "default",
    "label_placement": "top",
    "instruction_placement": "label",
    "hide_on_screen": "",
    "active": false,
    "description": "",
    "modified": 1617562026
}